thyroid_model_damir_bogdan/__init__.py
thyroid_model_damir_bogdan/create_pipeline.py
thyroid_model_damir_bogdan/label_encoder.joblib
thyroid_model_damir_bogdan/load_label_encoder.py
thyroid_model_damir_bogdan/load_pipeline.py
thyroid_model_damir_bogdan/pipeline.joblib
thyroid_model_damir_bogdan/raw.csv
thyroid_model_damir_bogdan/tests.py
thyroid_model_damir_bogdan-0.1.0.dist-info/LICENSE
thyroid_model_damir_bogdan-0.1.0.dist-info/METADATA
thyroid_model_damir_bogdan-0.1.0.dist-info/WHEEL
thyroid_model_damir_bogdan-0.1.0.dist-info/top_level.txt
thyroid_model_damir_bogdan-0.1.0.dist-info/RECORD
